main.py
modules/__init__.py
modules/home_screen.py
modules/video_player.py
utils/__init__.py
utils/image_utils.py
utils/os_utils.py
ascii_flix-0.24.dist-info/METADATA
ascii_flix-0.24.dist-info/WHEEL
ascii_flix-0.24.dist-info/entry_points.txt
ascii_flix-0.24.dist-info/top_level.txt
ascii_flix-0.24.dist-info/RECORD
