Metadata-Version: 2.1
Name: ascii_flix
Version: 0.24
Summary: A terminal-based video player that converts videos to ASCII art.
Author: Saad Ahmed Siddiqui
Requires-Python: >=3.6
Requires-Dist: pygame
Requires-Dist: moviepy
Requires-Dist: opencv-python
Requires-Dist: rich
Requires-Dist: numpy
Requires-Dist: windows-curses
